{"id":48,"title":"问：在Go项目开发中，你是否遇到过令人疑惑的坑点或Bug？最终是如何排查解决的？","slug":"问：在Go项目开发中，你是否遇到过令人疑惑的坑点或Bug？最终是如何排查解决的？-1766595048","content":"**参考回答：Go语言有一些新手容易踩到的坑，例如：循环变量捕获问题（在**`**for**`**循环中启动goroutine直接用循环变量，会导致闭包中引用的变量地址不变，每个goroutine拿到的值都一样）、slice扩容导致的底层数组重用问题、defer调用的执行时机等。可以结合实际谈一个Bug案例，比如：“我曾遇到过一个bug，预期启动10个goroutine处理10个不同任务，但结果每个goroutine处理的任务都是最后一个。后来发现是因为我在循环里直接用循环变量传给goroutine，导致闭包捕获了同一个变量引用。解决方法是在循环内部用局部变量保存当前值，或者将值作为参数传入goroutine的闭包函数，从而保证每个goroutine拿到不同的数据。” 通过这个例子展示你对Go细节的掌握和调试能力，并强调吸取的教训**（例如养成代码审查和单元测试的习惯，专门防范类似问题）。\n\n","excerpt":"","coverImageUrl":"","status":"PUBLISHED","createdAt":"2025-12-25T00:50:48+08:00","updatedAt":"2025-12-25T00:50:48+08:00","publishedAt":"2025-12-25T00:50:48+08:00","tags":[],"categories":[],"author":{"id":1,"username":"admin","avatar":""},"stats":{"viewCount":0,"likeCount":0,"commentCount":0,"updatedAt":"2025-12-25T00:54:02+08:00"}}