{"id":78,"title":"问：你认为AIGC（AI生成内容）技术在我们网易互动娱乐的产品中可以有哪些应用前景？你有没有什么创意的想法？","slug":"问：你认为AIGC（AI生成内容）技术在我们网易互动娱乐的产品中可以有哪些应用前景？你有没有什么创意的想法？-1766595060","content":"**参考回答：这个问题既考察对行业的了解也看重创新意识。可以结合网易互动娱乐的业务特点（游戏、社区、内容创作等）提出几种AIGC应用设想，例如：1）智能NPC对话：在游戏中引入大语言模型，让NPC能够与玩家进行自然对话、根据剧情即时生成个性化台词，提高沉浸感。2）游戏内容生成：利用AIGC生成游戏关卡、剧情支线或者道具描述，减少人力制作成本的同时提供更丰富的玩法。3）玩家社区：为社区论坛提供AI版主，自动回答常见问题或根据帖子内容生成总结，引导积极氛围。4）个性化推送：通过生成式AI为用户撰写个性化的新闻推送或活动通知，更有亲和力。回答时可以挑选一两个展开描述其可行性和价值，比如：“智能NPC对话可以基于现有的大模型微调游戏世界观语料，让NPC有自己的性格和背景，用自然语言与玩家互动，这将极大提升游戏代入感。” 展望类问题主要考验您的想象力**和对AIGC趋势的把握，思考得越深入、有新意，会给面试官留下深刻印象。\n\n","excerpt":"","coverImageUrl":"","status":"PUBLISHED","createdAt":"2025-12-25T00:51:00+08:00","updatedAt":"2025-12-25T00:51:00+08:00","publishedAt":"2025-12-25T00:51:00+08:00","tags":[],"categories":[],"author":{"id":1,"username":"admin","avatar":""},"stats":{"viewCount":0,"likeCount":0,"commentCount":0,"updatedAt":"2025-12-25T00:54:02+08:00"}}